{"events":[{"event":"call","http_server_request":{"headers":{"content-length":"85","host":"localhost:8080","content-type":"application/json","connection":"close","accept-encoding":"gzip, deflate, br","accept":"*/*","user-agent":"Thunder Client (https://www.thunderclient.com)"},"path_info":"/api/users","protocol":"HTTP/1.1","request_method":"POST"},"id":93495,"thread_id":187},{"defined_class":"id.bti.warehouse.controller.UserController","event":"call","id":93502,"lineno":39,"method_id":"saveUser","parameters":[{"class":"id.bti.warehouse.dto.request.UserRequest","kind":"req","name":"request","object_id":1013531909,"value":"id.bti.warehouse.dto.request.UserRequest@3c694505"}],"path":"src/main/java/id/bti/warehouse/controller/UserController.java","receiver":{"class":"id.bti.warehouse.controller.UserController","object_id":743539243,"value":"id.bti.warehouse.controller.UserController@2c51822b"},"static":false,"thread_id":187},{"defined_class":"id.bti.warehouse.service.UserService","event":"call","id":93503,"lineno":37,"method_id":"saveUser","parameters":[{"class":"id.bti.warehouse.dto.request.UserRequest","kind":"req","name":"userRequest","object_id":1013531909,"value":"id.bti.warehouse.dto.request.UserRequest@3c694505"}],"path":"src/main/java/id/bti/warehouse/service/UserService.java","receiver":{"class":"id.bti.warehouse.service.UserService","object_id":1261611676,"value":"id.bti.warehouse.service.UserService@4b32aa9c"},"static":false,"thread_id":187},{"defined_class":"id.bti.warehouse.repository.UserRepository","event":"call","id":93505,"lineno":-1,"method_id":"findByEmail","parameters":[{"class":"java.lang.String","kind":"req","name":"p0","object_id":945215056,"value":"ripal@mail.com"}],"path":"src/main/java/id/bti/warehouse/repository/UserRepository.java","receiver":{"class":"jdk.proxy10.$Proxy244","object_id":1507955975,"value":"org.springframework.data.jpa.repository.support.SimpleJpaRepository@757492e5"},"static":false,"thread_id":187},{"event":"call","id":93514,"sql_query":{"database_type":"PostgreSQL","sql":"select u1_0.id,u1_0.email,u1_0.full_name,u1_0.role from m_user u1_0 where u1_0.email=?"},"thread_id":187},{"elapsed":0.0,"event":"return","id":93515,"parent_id":93514,"thread_id":187},{"elapsed":1.698E-4,"event":"return","id":93517,"parent_id":93505,"return_value":{"class":"java.util.Optional","object_id":2142997110,"value":"Optional.empty"},"thread_id":187},{"event":"call","id":93531,"sql_query":{"database_type":"PostgreSQL","sql":"select nextval('m_user_seq')"},"thread_id":187},{"elapsed":0.0,"event":"return","id":93532,"parent_id":93531,"thread_id":187},{"elapsed":3.9879E-4,"event":"return","exceptions":[{"class":"org.springframework.orm.jpa.JpaSystemException","lineno":341,"message":"Unknown integral data type for ids : java.lang.String","object_id":422955435,"path":"HibernateJpaDialect.java"},{"class":"org.hibernate.id.IdentifierGenerationException","lineno":136,"message":"Unknown integral data type for ids : java.lang.String","object_id":436006469,"path":"IdentifierGeneratorHelper.java"}],"id":93540,"parent_id":93503,"thread_id":187},{"elapsed":4.5413E-4,"event":"return","id":93541,"parent_id":93502,"return_value":{"class":"org.springframework.http.ResponseEntity","object_id":479673807,"value":"<409 CONFLICT Conflict,Unknown integral data type for ids : java.lang.String,[]>"},"thread_id":187},{"elapsed":6.296E-4,"event":"return","http_server_response":{"headers":{"Connection":"close","Content-Length":"53","Date":"Thu, 01 Aug 2024 11:02:48 GMT","Content-Type":"text/plain;charset=UTF-8"},"status":409},"id":93562,"parent_id":93495,"thread_id":187}],"classMap":[{"children":[{"children":[{"children":[{"children":[{"children":[{"labels":[],"location":"src/main/java/id/bti/warehouse/service/UserService.java:37","name":"saveUser","static":false,"type":"function"}],"location":"src/main/java/id/bti/warehouse/service/UserService.java","name":"UserService","static":false,"type":"class"}],"name":"service","type":"package"},{"children":[{"children":[{"labels":[],"location":"src/main/java/id/bti/warehouse/controller/UserController.java:39","name":"saveUser","static":false,"type":"function"}],"location":"src/main/java/id/bti/warehouse/controller/UserController.java","name":"UserController","static":false,"type":"class"}],"name":"controller","type":"package"},{"children":[{"children":[{"labels":[],"location":"src/main/java/id/bti/warehouse/repository/UserRepository.java:-1","name":"findByEmail","static":false,"type":"function"}],"location":"src/main/java/id/bti/warehouse/repository/UserRepository.java","name":"UserRepository","static":false,"type":"class"}],"name":"repository","type":"package"}],"name":"warehouse","type":"package"}],"name":"bti","type":"package"}],"name":"id","type":"package"}],"version":"1.2","metadata":{"name":"POST /api/users (409) - 18:02:48.386","app":"warehouse","language":{"name":"java","version":"17.0.7+8-LTS-224","engine":"Java HotSpot(TM) 64-Bit Server VM"},"client":{"name":"appmap-java","url":"https://github.com/appland/appmap-java"},"recorder":{"name":"request_recording","type":"requests"},"recording":{},"git":{"repository":"https://github.com/Ripaldiansyah/api-warehouse-bti.git","branch":"main","commit":"0977c933ad37a6dcb6eb11f2d2c35ee22c65a69d"}},"eventUpdates":{"93495":{"event":"call","http_server_request":{"headers":{"content-length":"85","host":"localhost:8080","content-type":"application/json","connection":"close","accept-encoding":"gzip, deflate, br","accept":"*/*","user-agent":"Thunder Client (https://www.thunderclient.com)"},"normalized_path_info":"/api/users","path_info":"/api/users","protocol":"HTTP/1.1","request_method":"POST"},"id":93495,"thread_id":187}}}