{"events":[{"event":"call","http_server_request":{"headers":{"content-length":"199","host":"localhost:8080","content-type":"application/json","connection":"close","accept-encoding":"gzip, deflate, br","accept":"*/*","user-agent":"Thunder Client (https://www.thunderclient.com)"},"path_info":"/api/borrowings","protocol":"HTTP/1.1","request_method":"POST"},"id":174715,"thread_id":323},{"defined_class":"id.bti.warehouse.controller.BorrowingController","event":"call","id":174722,"lineno":26,"method_id":"borrowingProduct","parameters":[{"class":"id.bti.warehouse.dto.request.BorrowingRequest","kind":"req","name":"request","object_id":237313252,"value":"id.bti.warehouse.dto.request.BorrowingRequest@e251ce4"}],"path":"src/main/java/id/bti/warehouse/controller/BorrowingController.java","receiver":{"class":"id.bti.warehouse.controller.BorrowingController","object_id":277150481,"value":"id.bti.warehouse.controller.BorrowingController@1084fb11"},"static":false,"thread_id":323},{"defined_class":"id.bti.warehouse.service.BorrowingService","event":"call","id":174723,"lineno":28,"method_id":"borrowProduct","parameters":[{"class":"id.bti.warehouse.dto.request.BorrowingRequest","kind":"req","name":"request","object_id":237313252,"value":"id.bti.warehouse.dto.request.BorrowingRequest@e251ce4"}],"path":"src/main/java/id/bti/warehouse/service/BorrowingService.java","receiver":{"class":"id.bti.warehouse.service.BorrowingService","object_id":1195929871,"value":"id.bti.warehouse.service.BorrowingService@4748710f"},"static":false,"thread_id":323},{"event":"call","id":174729,"sql_query":{"database_type":"PostgreSQL","sql":""},"thread_id":323},{"elapsed":0.0,"event":"return","id":174730,"parent_id":174729,"thread_id":323},{"event":"call","id":174747,"sql_query":{"database_type":"PostgreSQL","sql":"select p1_0.id,p1_0.name,p1_0.product_type,p1_0.quantity from m_product p1_0 where p1_0.id=?"},"thread_id":323},{"elapsed":0.0,"event":"return","id":174748,"parent_id":174747,"thread_id":323},{"event":"call","id":174777,"sql_query":{"database_type":"PostgreSQL","sql":"select b1_0.id,b1_0.modified_date,p1_0.id,p1_0.name,p1_0.product_type,p1_0.quantity,b1_0.quantity,b1_0.status,u1_0.id,u1_0.email,u1_0.full_name,u1_0.role from m_borrowing b1_0 left join m_product p1_0 on p1_0.id=b1_0.product_id left join m_user u1_0 on u1_0.id=b1_0.user_id where b1_0.id=?"},"thread_id":323},{"elapsed":0.0,"event":"return","id":174778,"parent_id":174777,"thread_id":323},{"elapsed":4.0029E-4,"event":"return","exceptions":[{"class":"java.lang.RuntimeException","lineno":59,"message":"Quantity tidak cukup","object_id":639861141,"path":"BorrowingService.java"}],"id":174786,"parent_id":174723,"thread_id":323},{"elapsed":4.0029E-4,"event":"return","id":174787,"parent_id":174722,"return_value":{"class":"org.springframework.http.ResponseEntity","object_id":1474560241,"value":"<409 CONFLICT Conflict,Quantity tidak cukup,[]>"},"thread_id":323},{"elapsed":5.3006E-4,"event":"return","http_server_response":{"headers":{"Connection":"close","Content-Length":"20","Date":"Thu, 01 Aug 2024 11:06:47 GMT","Content-Type":"text/plain;charset=UTF-8"},"status":409},"id":174808,"parent_id":174715,"thread_id":323}],"classMap":[{"children":[{"children":[{"children":[{"children":[{"children":[{"labels":[],"location":"src/main/java/id/bti/warehouse/controller/BorrowingController.java:26","name":"borrowingProduct","static":false,"type":"function"}],"location":"src/main/java/id/bti/warehouse/controller/BorrowingController.java","name":"BorrowingController","static":false,"type":"class"}],"name":"controller","type":"package"},{"children":[{"children":[{"labels":[],"location":"src/main/java/id/bti/warehouse/service/BorrowingService.java:28","name":"borrowProduct","static":false,"type":"function"}],"location":"src/main/java/id/bti/warehouse/service/BorrowingService.java","name":"BorrowingService","static":false,"type":"class"}],"name":"service","type":"package"}],"name":"warehouse","type":"package"}],"name":"bti","type":"package"}],"name":"id","type":"package"}],"version":"1.2","metadata":{"name":"POST /api/borrowings (409) - 18:06:47.363","app":"warehouse","language":{"name":"java","version":"17.0.7+8-LTS-224","engine":"Java HotSpot(TM) 64-Bit Server VM"},"client":{"name":"appmap-java","url":"https://github.com/appland/appmap-java"},"recorder":{"name":"request_recording","type":"requests"},"recording":{},"git":{"repository":"https://github.com/Ripaldiansyah/api-warehouse-bti.git","branch":"main","commit":"0977c933ad37a6dcb6eb11f2d2c35ee22c65a69d"}},"eventUpdates":{"174715":{"event":"call","http_server_request":{"headers":{"content-length":"199","host":"localhost:8080","content-type":"application/json","connection":"close","accept-encoding":"gzip, deflate, br","accept":"*/*","user-agent":"Thunder Client (https://www.thunderclient.com)"},"normalized_path_info":"/api/borrowings","path_info":"/api/borrowings","protocol":"HTTP/1.1","request_method":"POST"},"id":174715,"thread_id":323}}}